mseep_wecom_bot_mcp_server-0.6.8.dist-info/licenses/LICENSE
tests/__init__.py
tests/conftest.py
tests/test_file.py
tests/test_image.py
tests/test_log_config.py
tests/test_markdown.py
tests/test_message.py
tests/test_server.py
tests/test_utils.py
mseep_wecom_bot_mcp_server-0.6.8.dist-info/METADATA
mseep_wecom_bot_mcp_server-0.6.8.dist-info/WHEEL
mseep_wecom_bot_mcp_server-0.6.8.dist-info/top_level.txt
mseep_wecom_bot_mcp_server-0.6.8.dist-info/RECORD
