Metadata-Version: 2.4
Name: mseep-wecom-bot-mcp-server
Version: 0.6.8
Summary: WeCom Bot MCP Server - A Python server for WeCom (WeChat Work) bot following the Model Context Protocol (MCP)
Home-page: 
Author: mseep
Author-email: support@skydeck.ai
Maintainer: mseep
Maintainer-email: support@skydeck.ai
Keywords: mseep
Classifier: Programming Language :: Python :: 3
Classifier: License :: OSI Approved :: MIT License
Classifier: Operating System :: OS Independent
Requires-Python: >=3.6
License-File: LICENSE
Requires-Dist: python
Requires-Dist: mcp
Requires-Dist: notify-bridge
Requires-Dist: platformdirs
Requires-Dist: pydantic
Requires-Dist: ftfy
Requires-Dist: httpx
Requires-Dist: pillow
Requires-Dist: svglib
Requires-Dist: tenacity
Requires-Dist: loguru
Requires-Dist: aiohttp
Dynamic: author
Dynamic: author-email
Dynamic: classifier
Dynamic: description
Dynamic: description-content-type
Dynamic: keywords
Dynamic: license-file
Dynamic: maintainer
Dynamic: maintainer-email
Dynamic: requires-dist
Dynamic: requires-python
Dynamic: summary
